{
  "system_id": "nordic_empire_1753478276",
  "system_name": "NORDIC EMPIRE DOMAIN ARCHITECTURE™",
  "founder": "MADS PALLISGAARD",
  "version": "1.0.0",
  "empire_status": "EXPANDING",
  "base_domain": "zoracore.ai",
  "total_domains": 10,
  "initialized_at": "2025-07-25T21:17:56.798695",
  "domains": {
    "denmark": {
      "full_domain": "dk.zoracore.ai",
      "country": "Denmark",
      "language": "da",
      "theme": "minimalism",
      "function": "Nordic Empire Headquarters",
      "priority": 1
    },
    "norway": {
      "full_domain": "no.zoracore.ai",
      "country": "Norway",
      "language": "no",
      "theme": "sustainability",
      "function": "Energy & Sustainability Innovation",
      "priority": 2
    },
    "sweden": {
      "full_domain": "se.zoracore.ai",
      "country": "Sweden",
      "language": "sv",
      "theme": "innovation",
      "function": "Technology & Startup Ecosystem",
      "priority": 3
    },
    "finland": {
      "full_domain": "fi.zoracore.ai",
      "country": "Finland",
      "language": "fi",
      "theme": "innovation",
      "function": "AI Research & Gaming Innovation",
      "priority": 4
    },
    "iceland": {
      "full_domain": "is.zoracore.ai",
      "country": "Iceland",
      "language": "is",
      "theme": "sustainability",
      "function": "Green Data Centers & Renewable Energy",
      "priority": 5
    },
    "business": {
      "full_domain": "business.zoracore.ai",
      "country": "Pan-Nordic",
      "language": "en",
      "theme": "innovation",
      "function": "Nordic Business Coordination",
      "priority": 6
    },
    "innovation": {
      "full_domain": "innovation.zoracore.ai",
      "country": "Pan-Nordic",
      "language": "en",
      "theme": "innovation",
      "function": "Nordic Innovation Laboratory",
      "priority": 7
    },
    "sustainability": {
      "full_domain": "sustainability.zoracore.ai",
      "country": "Pan-Nordic",
      "language": "en",
      "theme": "sustainability",
      "function": "Nordic Sustainability Center",
      "priority": 8
    },
    "culture": {
      "full_domain": "culture.zoracore.ai",
      "country": "Pan-Nordic",
      "language": "multi",
      "theme": "heritage",
      "function": "Nordic Cultural Heritage Platform",
      "priority": 9
    },
    "future": {
      "full_domain": "future.zoracore.ai",
      "country": "Pan-Nordic",
      "language": "en",
      "theme": "innovation",
      "function": "Nordic Future Vision Platform",
      "priority": 10
    }
  },
  "languages_supported": [
    "Danish",
    "Norwegian",
    "Swedish",
    "Finnish",
    "Icelandic"
  ],
  "cultural_themes": [
    "Nordic minimalist design",
    "Environmental consciousness",
    "Technological advancement",
    "Social equality values",
    "Cultural heritage preservation"
  ],
  "last_updated": "2025-07-25T21:17:56.798966"
}